{
  "slug": "feather-river-college",
  "name": "Feather River College",
  "url": "https://www.frc.edu/",
  "live": false,
  "courseCount": 0,
  "modalityCoverage": 0,
  "method": "sample",
  "source": "web-search-deep",
  "extractUrl": null,
  "status": "blocked",
  "lastStatus": "no real data yet",
  "reason": "Class schedule is behind a sign-in wall.",
  "courses": [
    {
      "code": "CIS 151",
      "title": "Programming in Python",
      "modality": "in_person",
      "term": "Fall 2026",
      "units": "4",
      "instructor": "Martinez",
      "section": "01N",
      "description": "Programming in Python — Computer Information Systems at Feather River College.",
      "url": "https://www.frc.edu/"
    },
    {
      "code": "CIS 103",
      "title": "Data Structures",
      "modality": "in_person",
      "term": "Fall 2026",
      "units": "3",
      "instructor": "Johnson",
      "section": "01H",
      "description": "Data Structures — Computer Information Systems at Feather River College.",
      "url": "https://www.frc.edu/"
    },
    {
      "code": "CIS 103",
      "title": "Data Structures",
      "modality": "in_person",
      "term": "Fall 2026",
      "units": "1",
      "instructor": "Rivera",
      "section": "02H",
      "description": "Data Structures — Computer Information Systems at Feather River College.",
      "url": "https://www.frc.edu/"
    },
    {
      "code": "CIS 103",
      "title": "Data Structures",
      "modality": "hybrid",
      "term": "Fall 2026",
      "units": "5",
      "instructor": "Anderson",
      "section": "03",
      "description": "Data Structures — Computer Information Systems at Feather River College.",
      "url": "https://www.frc.edu/"
    },
    {
      "code": "CIS 172",
      "title": "Web Development",
      "modality": "in_person",
      "term": "Fall 2026",
      "units": "2",
      "instructor": "Brown",
      "section": "01N",
      "description": "Web Development — Computer Information Systems at Feather River College.",
      "url": "https://www.frc.edu/"
    },
    {
      "code": "CIS 140",
      "title": "Cybersecurity Fundamentals",
      "modality": "hybrid",
      "term": "Fall 2026",
      "units": "2",
      "instructor": "Davis",
      "section": "01N",
      "description": "Cybersecurity Fundamentals — Computer Information Systems at Feather River College.",
      "url": "https://www.frc.edu/"
    },
    {
      "code": "CIS 140",
      "title": "Cybersecurity Fundamentals",
      "modality": "online",
      "term": "Fall 2026",
      "units": "5",
      "instructor": "Martinez",
      "section": "02W",
      "description": "Cybersecurity Fundamentals — Computer Information Systems at Feather River College.",
      "url": "https://www.frc.edu/"
    },
    {
      "code": "CIS 140",
      "title": "Cybersecurity Fundamentals",
      "modality": "online",
      "term": "Fall 2026",
      "units": "2",
      "instructor": "Khan",
      "section": "03",
      "description": "Cybersecurity Fundamentals — Computer Information Systems at Feather River College.",
      "url": "https://www.frc.edu/"
    },
    {
      "code": "CIS 295",
      "title": "JavaScript Programming",
      "modality": "online",
      "term": "Fall 2026",
      "units": "5",
      "instructor": "Martinez",
      "section": "01H",
      "description": "JavaScript Programming — Computer Information Systems at Feather River College.",
      "url": "https://www.frc.edu/"
    },
    {
      "code": "CIS 239",
      "title": "Networking Essentials",
      "modality": "online",
      "term": "Fall 2026",
      "units": "1",
      "instructor": "Garcia",
      "section": "01N",
      "description": "Networking Essentials — Computer Information Systems at Feather River College.",
      "url": "https://www.frc.edu/"
    },
    {
      "code": "CIS 239",
      "title": "Networking Essentials",
      "modality": "in_person",
      "term": "Fall 2026",
      "units": "4",
      "instructor": "Garcia",
      "section": "02N",
      "description": "Networking Essentials — Computer Information Systems at Feather River College.",
      "url": "https://www.frc.edu/"
    },
    {
      "code": "MATH 229",
      "title": "College Algebra",
      "modality": "in_person",
      "term": "Fall 2026",
      "units": "3",
      "instructor": "Nguyen",
      "section": "01",
      "description": "College Algebra — Mathematics at Feather River College.",
      "url": "https://www.frc.edu/"
    },
    {
      "code": "MATH 229",
      "title": "College Algebra",
      "modality": "hybrid",
      "term": "Fall 2026",
      "units": "3",
      "instructor": "Johnson",
      "section": "02H",
      "description": "College Algebra — Mathematics at Feather River College.",
      "url": "https://www.frc.edu/"
    },
    {
      "code": "MATH 256",
      "title": "Precalculus",
      "modality": "in_person",
      "term": "Fall 2026",
      "units": "1",
      "instructor": "Garcia",
      "section": "01N",
      "description": "Precalculus — Mathematics at Feather River College.",
      "url": "https://www.frc.edu/"
    },
    {
      "code": "MATH 298",
      "title": "Calculus II",
      "modality": "online",
      "term": "Fall 2026",
      "units": "2",
      "instructor": "Nguyen",
      "section": "01W",
      "description": "Calculus II — Mathematics at Feather River College.",
      "url": "https://www.frc.edu/"
    },
    {
      "code": "MATH 298",
      "title": "Calculus II",
      "modality": "in_person",
      "term": "Fall 2026",
      "units": "1",
      "instructor": "Martinez",
      "section": "02W",
      "description": "Calculus II — Mathematics at Feather River College.",
      "url": "https://www.frc.edu/"
    },
    {
      "code": "MATH 221",
      "title": "Statistics",
      "modality": "in_person",
      "term": "Fall 2026",
      "units": "2",
      "instructor": "Smith",
      "section": "01H",
      "description": "Statistics — Mathematics at Feather River College.",
      "url": "https://www.frc.edu/"
    },
    {
      "code": "MATH 221",
      "title": "Statistics",
      "modality": "online",
      "term": "Fall 2026",
      "units": "1",
      "instructor": "Nguyen",
      "section": "02H",
      "description": "Statistics — Mathematics at Feather River College.",
      "url": "https://www.frc.edu/"
    },
    {
      "code": "MATH 236",
      "title": "Trigonometry",
      "modality": "online",
      "term": "Fall 2026",
      "units": "1",
      "instructor": "Lee",
      "section": "01W",
      "description": "Trigonometry — Mathematics at Feather River College.",
      "url": "https://www.frc.edu/"
    },
    {
      "code": "MATH 132",
      "title": "Discrete Mathematics",
      "modality": "online",
      "term": "Fall 2026",
      "units": "1",
      "instructor": "Lopez",
      "section": "01H",
      "description": "Discrete Mathematics — Mathematics at Feather River College.",
      "url": "https://www.frc.edu/"
    },
    {
      "code": "MATH 132",
      "title": "Discrete Mathematics",
      "modality": "in_person",
      "term": "Fall 2026",
      "units": "1",
      "instructor": "Smith",
      "section": "02H",
      "description": "Discrete Mathematics — Mathematics at Feather River College.",
      "url": "https://www.frc.edu/"
    },
    {
      "code": "ENGL 224",
      "title": "College Composition",
      "modality": "online",
      "term": "Fall 2026",
      "units": "3",
      "instructor": "Lopez",
      "section": "01N",
      "description": "College Composition — English at Feather River College.",
      "url": "https://www.frc.edu/"
    },
    {
      "code": "ENGL 274",
      "title": "Technical Writing",
      "modality": "online",
      "term": "Fall 2026",
      "units": "5",
      "instructor": "Brown",
      "section": "01H",
      "description": "Technical Writing — English at Feather River College.",
      "url": "https://www.frc.edu/"
    },
    {
      "code": "ENGL 274",
      "title": "Technical Writing",
      "modality": "in_person",
      "term": "Fall 2026",
      "units": "2",
      "instructor": "Garcia",
      "section": "02W",
      "description": "Technical Writing — English at Feather River College.",
      "url": "https://www.frc.edu/"
    },
    {
      "code": "ENGL 135",
      "title": "Introduction to Poetry",
      "modality": "in_person",
      "term": "Fall 2026",
      "units": "1",
      "instructor": "Martinez",
      "section": "01N",
      "description": "Introduction to Poetry — English at Feather River College.",
      "url": "https://www.frc.edu/"
    },
    {
      "code": "BIOL 109",
      "title": "General Biology",
      "modality": "online",
      "term": "Fall 2026",
      "units": "3",
      "instructor": "Wong",
      "section": "01",
      "description": "General Biology — Biology at Feather River College.",
      "url": "https://www.frc.edu/"
    },
    {
      "code": "BIOL 109",
      "title": "General Biology",
      "modality": "hybrid",
      "term": "Fall 2026",
      "units": "2",
      "instructor": "Smith",
      "section": "02H",
      "description": "General Biology — Biology at Feather River College.",
      "url": "https://www.frc.edu/"
    },
    {
      "code": "BIOL 109",
      "title": "General Biology",
      "modality": "hybrid",
      "term": "Fall 2026",
      "units": "2",
      "instructor": "Khan",
      "section": "03N",
      "description": "General Biology — Biology at Feather River College.",
      "url": "https://www.frc.edu/"
    },
    {
      "code": "BIOL 154",
      "title": "Human Anatomy",
      "modality": "online",
      "term": "Fall 2026",
      "units": "1",
      "instructor": "Johnson",
      "section": "01N",
      "description": "Human Anatomy — Biology at Feather River College.",
      "url": "https://www.frc.edu/"
    },
    {
      "code": "BIOL 154",
      "title": "Human Anatomy",
      "modality": "online",
      "term": "Fall 2026",
      "units": "4",
      "instructor": "Davis",
      "section": "02W",
      "description": "Human Anatomy — Biology at Feather River College.",
      "url": "https://www.frc.edu/"
    },
    {
      "code": "BIOL 145",
      "title": "Microbiology",
      "modality": "in_person",
      "term": "Fall 2026",
      "units": "3",
      "instructor": "Johnson",
      "section": "01N",
      "description": "Microbiology — Biology at Feather River College.",
      "url": "https://www.frc.edu/"
    },
    {
      "code": "BIOL 291",
      "title": "Physiology",
      "modality": "hybrid",
      "term": "Fall 2026",
      "units": "1",
      "instructor": "Lopez",
      "section": "01",
      "description": "Physiology — Biology at Feather River College.",
      "url": "https://www.frc.edu/"
    },
    {
      "code": "BIOL 291",
      "title": "Physiology",
      "modality": "in_person",
      "term": "Fall 2026",
      "units": "5",
      "instructor": "Davis",
      "section": "02N",
      "description": "Physiology — Biology at Feather River College.",
      "url": "https://www.frc.edu/"
    },
    {
      "code": "BIOL 291",
      "title": "Physiology",
      "modality": "online",
      "term": "Fall 2026",
      "units": "4",
      "instructor": "Wong",
      "section": "03H",
      "description": "Physiology — Biology at Feather River College.",
      "url": "https://www.frc.edu/"
    },
    {
      "code": "BIOL 100",
      "title": "Marine Biology",
      "modality": "online",
      "term": "Fall 2026",
      "units": "4",
      "instructor": "Patel",
      "section": "01H",
      "description": "Marine Biology — Biology at Feather River College.",
      "url": "https://www.frc.edu/"
    },
    {
      "code": "BIOL 100",
      "title": "Marine Biology",
      "modality": "in_person",
      "term": "Fall 2026",
      "units": "2",
      "instructor": "Nguyen",
      "section": "02W",
      "description": "Marine Biology — Biology at Feather River College.",
      "url": "https://www.frc.edu/"
    },
    {
      "code": "BIOL 100",
      "title": "Marine Biology",
      "modality": "in_person",
      "term": "Fall 2026",
      "units": "3",
      "instructor": "Martinez",
      "section": "03W",
      "description": "Marine Biology — Biology at Feather River College.",
      "url": "https://www.frc.edu/"
    },
    {
      "code": "CHEM 186",
      "title": "General Chemistry",
      "modality": "hybrid",
      "term": "Fall 2026",
      "units": "4",
      "instructor": "Khan",
      "section": "01",
      "description": "General Chemistry — Chemistry at Feather River College.",
      "url": "https://www.frc.edu/"
    },
    {
      "code": "CHEM 186",
      "title": "General Chemistry",
      "modality": "online",
      "term": "Fall 2026",
      "units": "2",
      "instructor": "Nguyen",
      "section": "02",
      "description": "General Chemistry — Chemistry at Feather River College.",
      "url": "https://www.frc.edu/"
    },
    {
      "code": "CHEM 186",
      "title": "General Chemistry",
      "modality": "online",
      "term": "Fall 2026",
      "units": "5",
      "instructor": "Khan",
      "section": "03W",
      "description": "General Chemistry — Chemistry at Feather River College.",
      "url": "https://www.frc.edu/"
    },
    {
      "code": "CHEM 219",
      "title": "Organic Chemistry",
      "modality": "in_person",
      "term": "Fall 2026",
      "units": "3",
      "instructor": "Rivera",
      "section": "01",
      "description": "Organic Chemistry — Chemistry at Feather River College.",
      "url": "https://www.frc.edu/"
    },
    {
      "code": "CHEM 219",
      "title": "Organic Chemistry",
      "modality": "in_person",
      "term": "Fall 2026",
      "units": "3",
      "instructor": "Wong",
      "section": "02H",
      "description": "Organic Chemistry — Chemistry at Feather River College.",
      "url": "https://www.frc.edu/"
    },
    {
      "code": "CHEM 219",
      "title": "Organic Chemistry",
      "modality": "hybrid",
      "term": "Fall 2026",
      "units": "5",
      "instructor": "Chen",
      "section": "03N",
      "description": "Organic Chemistry — Chemistry at Feather River College.",
      "url": "https://www.frc.edu/"
    },
    {
      "code": "CHEM 217",
      "title": "Biochemistry",
      "modality": "online",
      "term": "Fall 2026",
      "units": "2",
      "instructor": "Chen",
      "section": "01N",
      "description": "Biochemistry — Chemistry at Feather River College.",
      "url": "https://www.frc.edu/"
    },
    {
      "code": "PSYC 206",
      "title": "Introduction to Psychology",
      "modality": "online",
      "term": "Fall 2026",
      "units": "1",
      "instructor": "Wong",
      "section": "01W",
      "description": "Introduction to Psychology — Psychology at Feather River College.",
      "url": "https://www.frc.edu/"
    },
    {
      "code": "PSYC 206",
      "title": "Introduction to Psychology",
      "modality": "hybrid",
      "term": "Fall 2026",
      "units": "2",
      "instructor": "Patel",
      "section": "02W",
      "description": "Introduction to Psychology — Psychology at Feather River College.",
      "url": "https://www.frc.edu/"
    },
    {
      "code": "PSYC 250",
      "title": "Developmental Psychology",
      "modality": "online",
      "term": "Fall 2026",
      "units": "2",
      "instructor": "Anderson",
      "section": "01W",
      "description": "Developmental Psychology — Psychology at Feather River College.",
      "url": "https://www.frc.edu/"
    },
    {
      "code": "PSYC 250",
      "title": "Developmental Psychology",
      "modality": "hybrid",
      "term": "Fall 2026",
      "units": "2",
      "instructor": "Anderson",
      "section": "02",
      "description": "Developmental Psychology — Psychology at Feather River College.",
      "url": "https://www.frc.edu/"
    },
    {
      "code": "PSYC 250",
      "title": "Developmental Psychology",
      "modality": "online",
      "term": "Fall 2026",
      "units": "3",
      "instructor": "Patel",
      "section": "03H",
      "description": "Developmental Psychology — Psychology at Feather River College.",
      "url": "https://www.frc.edu/"
    },
    {
      "code": "PSYC 107",
      "title": "Abnormal Psychology",
      "modality": "online",
      "term": "Fall 2026",
      "units": "4",
      "instructor": "Nguyen",
      "section": "01W",
      "description": "Abnormal Psychology — Psychology at Feather River College.",
      "url": "https://www.frc.edu/"
    },
    {
      "code": "PSYC 265",
      "title": "Social Psychology",
      "modality": "online",
      "term": "Fall 2026",
      "units": "4",
      "instructor": "Lee",
      "section": "01H",
      "description": "Social Psychology — Psychology at Feather River College.",
      "url": "https://www.frc.edu/"
    },
    {
      "code": "BUS 194",
      "title": "Introduction to Business",
      "modality": "in_person",
      "term": "Fall 2026",
      "units": "3",
      "instructor": "Smith",
      "section": "01H",
      "description": "Introduction to Business — Business at Feather River College.",
      "url": "https://www.frc.edu/"
    },
    {
      "code": "BUS 101",
      "title": "Principles of Management",
      "modality": "hybrid",
      "term": "Fall 2026",
      "units": "1",
      "instructor": "Smith",
      "section": "01H",
      "description": "Principles of Management — Business at Feather River College.",
      "url": "https://www.frc.edu/"
    },
    {
      "code": "BUS 101",
      "title": "Principles of Management",
      "modality": "online",
      "term": "Fall 2026",
      "units": "3",
      "instructor": "Patel",
      "section": "02N",
      "description": "Principles of Management — Business at Feather River College.",
      "url": "https://www.frc.edu/"
    },
    {
      "code": "BUS 197",
      "title": "Marketing",
      "modality": "in_person",
      "term": "Fall 2026",
      "units": "3",
      "instructor": "Nguyen",
      "section": "01H",
      "description": "Marketing — Business at Feather River College.",
      "url": "https://www.frc.edu/"
    },
    {
      "code": "BUS 107",
      "title": "Accounting Principles",
      "modality": "in_person",
      "term": "Fall 2026",
      "units": "5",
      "instructor": "Anderson",
      "section": "01",
      "description": "Accounting Principles — Business at Feather River College.",
      "url": "https://www.frc.edu/"
    },
    {
      "code": "BUS 107",
      "title": "Accounting Principles",
      "modality": "hybrid",
      "term": "Fall 2026",
      "units": "5",
      "instructor": "Davis",
      "section": "02H",
      "description": "Accounting Principles — Business at Feather River College.",
      "url": "https://www.frc.edu/"
    },
    {
      "code": "ART 214",
      "title": "Drawing I",
      "modality": "hybrid",
      "term": "Fall 2026",
      "units": "1",
      "instructor": "Rivera",
      "section": "01H",
      "description": "Drawing I — Art at Feather River College.",
      "url": "https://www.frc.edu/"
    },
    {
      "code": "ART 269",
      "title": "Digital Photography",
      "modality": "hybrid",
      "term": "Fall 2026",
      "units": "1",
      "instructor": "Lopez",
      "section": "01W",
      "description": "Digital Photography — Art at Feather River College.",
      "url": "https://www.frc.edu/"
    },
    {
      "code": "ART 269",
      "title": "Graphic Design",
      "modality": "hybrid",
      "term": "Fall 2026",
      "units": "5",
      "instructor": "Brown",
      "section": "01",
      "description": "Graphic Design — Art at Feather River College.",
      "url": "https://www.frc.edu/"
    },
    {
      "code": "ART 269",
      "title": "Graphic Design",
      "modality": "online",
      "term": "Fall 2026",
      "units": "5",
      "instructor": "Nguyen",
      "section": "02H",
      "description": "Graphic Design — Art at Feather River College.",
      "url": "https://www.frc.edu/"
    },
    {
      "code": "ART 269",
      "title": "Graphic Design",
      "modality": "in_person",
      "term": "Fall 2026",
      "units": "2",
      "instructor": "Lopez",
      "section": "03W",
      "description": "Graphic Design — Art at Feather River College.",
      "url": "https://www.frc.edu/"
    },
    {
      "code": "HIST 163",
      "title": "US History",
      "modality": "online",
      "term": "Fall 2026",
      "units": "4",
      "instructor": "Chen",
      "section": "01N",
      "description": "US History — History at Feather River College.",
      "url": "https://www.frc.edu/"
    },
    {
      "code": "HIST 163",
      "title": "US History",
      "modality": "hybrid",
      "term": "Fall 2026",
      "units": "1",
      "instructor": "Johnson",
      "section": "02",
      "description": "US History — History at Feather River College.",
      "url": "https://www.frc.edu/"
    },
    {
      "code": "HIST 125",
      "title": "World History",
      "modality": "hybrid",
      "term": "Fall 2026",
      "units": "3",
      "instructor": "Wong",
      "section": "01W",
      "description": "World History — History at Feather River College.",
      "url": "https://www.frc.edu/"
    },
    {
      "code": "HIST 200",
      "title": "California History",
      "modality": "in_person",
      "term": "Fall 2026",
      "units": "1",
      "instructor": "Anderson",
      "section": "01W",
      "description": "California History — History at Feather River College.",
      "url": "https://www.frc.edu/"
    },
    {
      "code": "HIST 200",
      "title": "California History",
      "modality": "online",
      "term": "Fall 2026",
      "units": "2",
      "instructor": "Johnson",
      "section": "02N",
      "description": "California History — History at Feather River College.",
      "url": "https://www.frc.edu/"
    },
    {
      "code": "COMM 268",
      "title": "Interpersonal Communication",
      "modality": "online",
      "term": "Fall 2026",
      "units": "2",
      "instructor": "Khan",
      "section": "01",
      "description": "Interpersonal Communication — Communication Studies at Feather River College.",
      "url": "https://www.frc.edu/"
    },
    {
      "code": "COMM 268",
      "title": "Interpersonal Communication",
      "modality": "online",
      "term": "Fall 2026",
      "units": "5",
      "instructor": "Brown",
      "section": "02H",
      "description": "Interpersonal Communication — Communication Studies at Feather River College.",
      "url": "https://www.frc.edu/"
    },
    {
      "code": "COMM 268",
      "title": "Interpersonal Communication",
      "modality": "online",
      "term": "Fall 2026",
      "units": "4",
      "instructor": "Garcia",
      "section": "03N",
      "description": "Interpersonal Communication — Communication Studies at Feather River College.",
      "url": "https://www.frc.edu/"
    },
    {
      "code": "COMM 282",
      "title": "Mass Media",
      "modality": "hybrid",
      "term": "Fall 2026",
      "units": "1",
      "instructor": "Patel",
      "section": "01",
      "description": "Mass Media — Communication Studies at Feather River College.",
      "url": "https://www.frc.edu/"
    },
    {
      "code": "COMM 119",
      "title": "Small Group Communication",
      "modality": "hybrid",
      "term": "Fall 2026",
      "units": "3",
      "instructor": "Lee",
      "section": "01W",
      "description": "Small Group Communication — Communication Studies at Feather River College.",
      "url": "https://www.frc.edu/"
    },
    {
      "code": "COMM 119",
      "title": "Small Group Communication",
      "modality": "hybrid",
      "term": "Fall 2026",
      "units": "4",
      "instructor": "Smith",
      "section": "02W",
      "description": "Small Group Communication — Communication Studies at Feather River College.",
      "url": "https://www.frc.edu/"
    },
    {
      "code": "NURS 118",
      "title": "Fundamentals of Nursing",
      "modality": "hybrid",
      "term": "Fall 2026",
      "units": "3",
      "instructor": "Khan",
      "section": "01W",
      "description": "Fundamentals of Nursing — Nursing at Feather River College.",
      "url": "https://www.frc.edu/"
    },
    {
      "code": "NURS 118",
      "title": "Fundamentals of Nursing",
      "modality": "hybrid",
      "term": "Fall 2026",
      "units": "4",
      "instructor": "Nguyen",
      "section": "02H",
      "description": "Fundamentals of Nursing — Nursing at Feather River College.",
      "url": "https://www.frc.edu/"
    },
    {
      "code": "NURS 168",
      "title": "Pharmacology",
      "modality": "hybrid",
      "term": "Fall 2026",
      "units": "2",
      "instructor": "Davis",
      "section": "01W",
      "description": "Pharmacology — Nursing at Feather River College.",
      "url": "https://www.frc.edu/"
    },
    {
      "code": "NURS 168",
      "title": "Pharmacology",
      "modality": "in_person",
      "term": "Fall 2026",
      "units": "1",
      "instructor": "Brown",
      "section": "02H",
      "description": "Pharmacology — Nursing at Feather River College.",
      "url": "https://www.frc.edu/"
    },
    {
      "code": "NURS 168",
      "title": "Pharmacology",
      "modality": "in_person",
      "term": "Fall 2026",
      "units": "1",
      "instructor": "Rivera",
      "section": "03H",
      "description": "Pharmacology — Nursing at Feather River College.",
      "url": "https://www.frc.edu/"
    },
    {
      "code": "NURS 278",
      "title": "Maternal-Newborn Nursing",
      "modality": "in_person",
      "term": "Fall 2026",
      "units": "1",
      "instructor": "Brown",
      "section": "01",
      "description": "Maternal-Newborn Nursing — Nursing at Feather River College.",
      "url": "https://www.frc.edu/"
    },
    {
      "code": "NURS 278",
      "title": "Maternal-Newborn Nursing",
      "modality": "in_person",
      "term": "Fall 2026",
      "units": "2",
      "instructor": "Chen",
      "section": "02N",
      "description": "Maternal-Newborn Nursing — Nursing at Feather River College.",
      "url": "https://www.frc.edu/"
    },
    {
      "code": "NURS 278",
      "title": "Maternal-Newborn Nursing",
      "modality": "hybrid",
      "term": "Fall 2026",
      "units": "5",
      "instructor": "Wong",
      "section": "03",
      "description": "Maternal-Newborn Nursing — Nursing at Feather River College.",
      "url": "https://www.frc.edu/"
    },
    {
      "code": "PHYS 182",
      "title": "General Physics",
      "modality": "in_person",
      "term": "Fall 2026",
      "units": "4",
      "instructor": "Lee",
      "section": "01H",
      "description": "General Physics — Physics at Feather River College.",
      "url": "https://www.frc.edu/"
    },
    {
      "code": "PHYS 182",
      "title": "General Physics",
      "modality": "hybrid",
      "term": "Fall 2026",
      "units": "5",
      "instructor": "Chen",
      "section": "02H",
      "description": "General Physics — Physics at Feather River College.",
      "url": "https://www.frc.edu/"
    },
    {
      "code": "PHYS 225",
      "title": "Physics for Scientists and Engineers",
      "modality": "online",
      "term": "Fall 2026",
      "units": "1",
      "instructor": "Patel",
      "section": "01H",
      "description": "Physics for Scientists and Engineers — Physics at Feather River College.",
      "url": "https://www.frc.edu/"
    }
  ]
}