{
  "slug": "santa-ana-college",
  "name": "Santa Ana College",
  "url": "https://www.sac.edu/",
  "live": false,
  "courseCount": 0,
  "modalityCoverage": 0,
  "method": "sample",
  "source": "homepage",
  "extractUrl": null,
  "status": "impossible",
  "lastStatus": "no real data yet",
  "reason": "No public, login-free schedule found (likely a JS app, a PDF, or login-gated).",
  "courses": [
    {
      "code": "CIS 296",
      "title": "Introduction to Computer Science",
      "modality": "hybrid",
      "term": "Fall 2026",
      "units": "3",
      "instructor": "Martinez",
      "section": "01",
      "description": "Introduction to Computer Science — Computer Information Systems at Santa Ana College.",
      "url": "https://www.sac.edu/"
    },
    {
      "code": "CIS 228",
      "title": "Programming in Python",
      "modality": "hybrid",
      "term": "Fall 2026",
      "units": "3",
      "instructor": "Patel",
      "section": "01",
      "description": "Programming in Python — Computer Information Systems at Santa Ana College.",
      "url": "https://www.sac.edu/"
    },
    {
      "code": "CIS 228",
      "title": "Programming in Python",
      "modality": "in_person",
      "term": "Fall 2026",
      "units": "1",
      "instructor": "Lee",
      "section": "02N",
      "description": "Programming in Python — Computer Information Systems at Santa Ana College.",
      "url": "https://www.sac.edu/"
    },
    {
      "code": "CIS 132",
      "title": "Data Structures",
      "modality": "in_person",
      "term": "Fall 2026",
      "units": "1",
      "instructor": "Rivera",
      "section": "01",
      "description": "Data Structures — Computer Information Systems at Santa Ana College.",
      "url": "https://www.sac.edu/"
    },
    {
      "code": "CIS 132",
      "title": "Data Structures",
      "modality": "hybrid",
      "term": "Fall 2026",
      "units": "3",
      "instructor": "Chen",
      "section": "02",
      "description": "Data Structures — Computer Information Systems at Santa Ana College.",
      "url": "https://www.sac.edu/"
    },
    {
      "code": "CIS 148",
      "title": "Web Development",
      "modality": "online",
      "term": "Fall 2026",
      "units": "3",
      "instructor": "Garcia",
      "section": "01H",
      "description": "Web Development — Computer Information Systems at Santa Ana College.",
      "url": "https://www.sac.edu/"
    },
    {
      "code": "CIS 148",
      "title": "Web Development",
      "modality": "hybrid",
      "term": "Fall 2026",
      "units": "1",
      "instructor": "Anderson",
      "section": "02N",
      "description": "Web Development — Computer Information Systems at Santa Ana College.",
      "url": "https://www.sac.edu/"
    },
    {
      "code": "CIS 148",
      "title": "Web Development",
      "modality": "hybrid",
      "term": "Fall 2026",
      "units": "3",
      "instructor": "Wong",
      "section": "03H",
      "description": "Web Development — Computer Information Systems at Santa Ana College.",
      "url": "https://www.sac.edu/"
    },
    {
      "code": "CIS 270",
      "title": "JavaScript Programming",
      "modality": "hybrid",
      "term": "Fall 2026",
      "units": "1",
      "instructor": "Garcia",
      "section": "01N",
      "description": "JavaScript Programming — Computer Information Systems at Santa Ana College.",
      "url": "https://www.sac.edu/"
    },
    {
      "code": "CIS 228",
      "title": "Networking Essentials",
      "modality": "hybrid",
      "term": "Fall 2026",
      "units": "3",
      "instructor": "Lopez",
      "section": "01",
      "description": "Networking Essentials — Computer Information Systems at Santa Ana College.",
      "url": "https://www.sac.edu/"
    },
    {
      "code": "MATH 177",
      "title": "College Algebra",
      "modality": "hybrid",
      "term": "Fall 2026",
      "units": "5",
      "instructor": "Brown",
      "section": "01H",
      "description": "College Algebra — Mathematics at Santa Ana College.",
      "url": "https://www.sac.edu/"
    },
    {
      "code": "MATH 177",
      "title": "College Algebra",
      "modality": "in_person",
      "term": "Fall 2026",
      "units": "2",
      "instructor": "Patel",
      "section": "02W",
      "description": "College Algebra — Mathematics at Santa Ana College.",
      "url": "https://www.sac.edu/"
    },
    {
      "code": "MATH 177",
      "title": "College Algebra",
      "modality": "hybrid",
      "term": "Fall 2026",
      "units": "5",
      "instructor": "Davis",
      "section": "03",
      "description": "College Algebra — Mathematics at Santa Ana College.",
      "url": "https://www.sac.edu/"
    },
    {
      "code": "MATH 173",
      "title": "Trigonometry",
      "modality": "online",
      "term": "Fall 2026",
      "units": "4",
      "instructor": "Garcia",
      "section": "01",
      "description": "Trigonometry — Mathematics at Santa Ana College.",
      "url": "https://www.sac.edu/"
    },
    {
      "code": "MATH 173",
      "title": "Trigonometry",
      "modality": "in_person",
      "term": "Fall 2026",
      "units": "1",
      "instructor": "Khan",
      "section": "02H",
      "description": "Trigonometry — Mathematics at Santa Ana College.",
      "url": "https://www.sac.edu/"
    },
    {
      "code": "MATH 186",
      "title": "Linear Algebra",
      "modality": "online",
      "term": "Fall 2026",
      "units": "3",
      "instructor": "Davis",
      "section": "01",
      "description": "Linear Algebra — Mathematics at Santa Ana College.",
      "url": "https://www.sac.edu/"
    },
    {
      "code": "MATH 186",
      "title": "Linear Algebra",
      "modality": "hybrid",
      "term": "Fall 2026",
      "units": "4",
      "instructor": "Smith",
      "section": "02W",
      "description": "Linear Algebra — Mathematics at Santa Ana College.",
      "url": "https://www.sac.edu/"
    },
    {
      "code": "MATH 186",
      "title": "Linear Algebra",
      "modality": "hybrid",
      "term": "Fall 2026",
      "units": "2",
      "instructor": "Martinez",
      "section": "03",
      "description": "Linear Algebra — Mathematics at Santa Ana College.",
      "url": "https://www.sac.edu/"
    },
    {
      "code": "MATH 213",
      "title": "Discrete Mathematics",
      "modality": "hybrid",
      "term": "Fall 2026",
      "units": "5",
      "instructor": "Brown",
      "section": "01W",
      "description": "Discrete Mathematics — Mathematics at Santa Ana College.",
      "url": "https://www.sac.edu/"
    },
    {
      "code": "MATH 213",
      "title": "Discrete Mathematics",
      "modality": "hybrid",
      "term": "Fall 2026",
      "units": "3",
      "instructor": "Anderson",
      "section": "02H",
      "description": "Discrete Mathematics — Mathematics at Santa Ana College.",
      "url": "https://www.sac.edu/"
    },
    {
      "code": "ENGL 220",
      "title": "College Composition",
      "modality": "in_person",
      "term": "Fall 2026",
      "units": "3",
      "instructor": "Khan",
      "section": "01",
      "description": "College Composition — English at Santa Ana College.",
      "url": "https://www.sac.edu/"
    },
    {
      "code": "ENGL 220",
      "title": "College Composition",
      "modality": "online",
      "term": "Fall 2026",
      "units": "1",
      "instructor": "Johnson",
      "section": "02W",
      "description": "College Composition — English at Santa Ana College.",
      "url": "https://www.sac.edu/"
    },
    {
      "code": "ENGL 195",
      "title": "Critical Thinking",
      "modality": "online",
      "term": "Fall 2026",
      "units": "1",
      "instructor": "Martinez",
      "section": "01",
      "description": "Critical Thinking — English at Santa Ana College.",
      "url": "https://www.sac.edu/"
    },
    {
      "code": "ENGL 195",
      "title": "Critical Thinking",
      "modality": "in_person",
      "term": "Fall 2026",
      "units": "5",
      "instructor": "Patel",
      "section": "02",
      "description": "Critical Thinking — English at Santa Ana College.",
      "url": "https://www.sac.edu/"
    },
    {
      "code": "ENGL 195",
      "title": "Critical Thinking",
      "modality": "online",
      "term": "Fall 2026",
      "units": "1",
      "instructor": "Wong",
      "section": "03H",
      "description": "Critical Thinking — English at Santa Ana College.",
      "url": "https://www.sac.edu/"
    },
    {
      "code": "ENGL 285",
      "title": "American Literature",
      "modality": "hybrid",
      "term": "Fall 2026",
      "units": "5",
      "instructor": "Martinez",
      "section": "01W",
      "description": "American Literature — English at Santa Ana College.",
      "url": "https://www.sac.edu/"
    },
    {
      "code": "ENGL 285",
      "title": "American Literature",
      "modality": "online",
      "term": "Fall 2026",
      "units": "4",
      "instructor": "Chen",
      "section": "02H",
      "description": "American Literature — English at Santa Ana College.",
      "url": "https://www.sac.edu/"
    },
    {
      "code": "ENGL 285",
      "title": "American Literature",
      "modality": "in_person",
      "term": "Fall 2026",
      "units": "4",
      "instructor": "Brown",
      "section": "03H",
      "description": "American Literature — English at Santa Ana College.",
      "url": "https://www.sac.edu/"
    },
    {
      "code": "ENGL 117",
      "title": "Technical Writing",
      "modality": "in_person",
      "term": "Fall 2026",
      "units": "2",
      "instructor": "Davis",
      "section": "01H",
      "description": "Technical Writing — English at Santa Ana College.",
      "url": "https://www.sac.edu/"
    },
    {
      "code": "ENGL 117",
      "title": "Technical Writing",
      "modality": "hybrid",
      "term": "Fall 2026",
      "units": "3",
      "instructor": "Anderson",
      "section": "02W",
      "description": "Technical Writing — English at Santa Ana College.",
      "url": "https://www.sac.edu/"
    },
    {
      "code": "ENGL 117",
      "title": "Technical Writing",
      "modality": "hybrid",
      "term": "Fall 2026",
      "units": "3",
      "instructor": "Lee",
      "section": "03W",
      "description": "Technical Writing — English at Santa Ana College.",
      "url": "https://www.sac.edu/"
    },
    {
      "code": "ENGL 272",
      "title": "Introduction to Poetry",
      "modality": "in_person",
      "term": "Fall 2026",
      "units": "3",
      "instructor": "Davis",
      "section": "01H",
      "description": "Introduction to Poetry — English at Santa Ana College.",
      "url": "https://www.sac.edu/"
    },
    {
      "code": "ENGL 272",
      "title": "Introduction to Poetry",
      "modality": "in_person",
      "term": "Fall 2026",
      "units": "2",
      "instructor": "Smith",
      "section": "02W",
      "description": "Introduction to Poetry — English at Santa Ana College.",
      "url": "https://www.sac.edu/"
    },
    {
      "code": "BIOL 144",
      "title": "General Biology",
      "modality": "hybrid",
      "term": "Fall 2026",
      "units": "3",
      "instructor": "Martinez",
      "section": "01H",
      "description": "General Biology — Biology at Santa Ana College.",
      "url": "https://www.sac.edu/"
    },
    {
      "code": "BIOL 144",
      "title": "General Biology",
      "modality": "hybrid",
      "term": "Fall 2026",
      "units": "2",
      "instructor": "Lopez",
      "section": "02H",
      "description": "General Biology — Biology at Santa Ana College.",
      "url": "https://www.sac.edu/"
    },
    {
      "code": "BIOL 144",
      "title": "General Biology",
      "modality": "in_person",
      "term": "Fall 2026",
      "units": "1",
      "instructor": "Nguyen",
      "section": "03N",
      "description": "General Biology — Biology at Santa Ana College.",
      "url": "https://www.sac.edu/"
    },
    {
      "code": "BIOL 164",
      "title": "Microbiology",
      "modality": "hybrid",
      "term": "Fall 2026",
      "units": "5",
      "instructor": "Garcia",
      "section": "01",
      "description": "Microbiology — Biology at Santa Ana College.",
      "url": "https://www.sac.edu/"
    },
    {
      "code": "BIOL 164",
      "title": "Microbiology",
      "modality": "hybrid",
      "term": "Fall 2026",
      "units": "4",
      "instructor": "Khan",
      "section": "02W",
      "description": "Microbiology — Biology at Santa Ana College.",
      "url": "https://www.sac.edu/"
    },
    {
      "code": "BIOL 287",
      "title": "Genetics",
      "modality": "in_person",
      "term": "Fall 2026",
      "units": "5",
      "instructor": "Chen",
      "section": "01W",
      "description": "Genetics — Biology at Santa Ana College.",
      "url": "https://www.sac.edu/"
    },
    {
      "code": "BIOL 287",
      "title": "Genetics",
      "modality": "in_person",
      "term": "Fall 2026",
      "units": "3",
      "instructor": "Lee",
      "section": "02",
      "description": "Genetics — Biology at Santa Ana College.",
      "url": "https://www.sac.edu/"
    },
    {
      "code": "PSYC 167",
      "title": "Developmental Psychology",
      "modality": "hybrid",
      "term": "Fall 2026",
      "units": "4",
      "instructor": "Lopez",
      "section": "01",
      "description": "Developmental Psychology — Psychology at Santa Ana College.",
      "url": "https://www.sac.edu/"
    },
    {
      "code": "PSYC 182",
      "title": "Social Psychology",
      "modality": "online",
      "term": "Fall 2026",
      "units": "2",
      "instructor": "Anderson",
      "section": "01",
      "description": "Social Psychology — Psychology at Santa Ana College.",
      "url": "https://www.sac.edu/"
    },
    {
      "code": "PSYC 182",
      "title": "Social Psychology",
      "modality": "hybrid",
      "term": "Fall 2026",
      "units": "3",
      "instructor": "Garcia",
      "section": "02N",
      "description": "Social Psychology — Psychology at Santa Ana College.",
      "url": "https://www.sac.edu/"
    },
    {
      "code": "BUS 194",
      "title": "Introduction to Business",
      "modality": "online",
      "term": "Fall 2026",
      "units": "4",
      "instructor": "Wong",
      "section": "01",
      "description": "Introduction to Business — Business at Santa Ana College.",
      "url": "https://www.sac.edu/"
    },
    {
      "code": "BUS 194",
      "title": "Introduction to Business",
      "modality": "online",
      "term": "Fall 2026",
      "units": "1",
      "instructor": "Lee",
      "section": "02",
      "description": "Introduction to Business — Business at Santa Ana College.",
      "url": "https://www.sac.edu/"
    },
    {
      "code": "BUS 194",
      "title": "Introduction to Business",
      "modality": "hybrid",
      "term": "Fall 2026",
      "units": "5",
      "instructor": "Davis",
      "section": "03W",
      "description": "Introduction to Business — Business at Santa Ana College.",
      "url": "https://www.sac.edu/"
    },
    {
      "code": "BUS 154",
      "title": "Principles of Management",
      "modality": "in_person",
      "term": "Fall 2026",
      "units": "1",
      "instructor": "Wong",
      "section": "01H",
      "description": "Principles of Management — Business at Santa Ana College.",
      "url": "https://www.sac.edu/"
    },
    {
      "code": "BUS 154",
      "title": "Principles of Management",
      "modality": "online",
      "term": "Fall 2026",
      "units": "2",
      "instructor": "Martinez",
      "section": "02N",
      "description": "Principles of Management — Business at Santa Ana College.",
      "url": "https://www.sac.edu/"
    },
    {
      "code": "BUS 123",
      "title": "Marketing",
      "modality": "hybrid",
      "term": "Fall 2026",
      "units": "2",
      "instructor": "Rivera",
      "section": "01W",
      "description": "Marketing — Business at Santa Ana College.",
      "url": "https://www.sac.edu/"
    },
    {
      "code": "BUS 123",
      "title": "Marketing",
      "modality": "hybrid",
      "term": "Fall 2026",
      "units": "1",
      "instructor": "Patel",
      "section": "02W",
      "description": "Marketing — Business at Santa Ana College.",
      "url": "https://www.sac.edu/"
    },
    {
      "code": "BUS 123",
      "title": "Marketing",
      "modality": "hybrid",
      "term": "Fall 2026",
      "units": "2",
      "instructor": "Patel",
      "section": "03N",
      "description": "Marketing — Business at Santa Ana College.",
      "url": "https://www.sac.edu/"
    },
    {
      "code": "BUS 161",
      "title": "Business Law",
      "modality": "hybrid",
      "term": "Fall 2026",
      "units": "1",
      "instructor": "Brown",
      "section": "01",
      "description": "Business Law — Business at Santa Ana College.",
      "url": "https://www.sac.edu/"
    },
    {
      "code": "BUS 157",
      "title": "Accounting Principles",
      "modality": "online",
      "term": "Fall 2026",
      "units": "5",
      "instructor": "Smith",
      "section": "01N",
      "description": "Accounting Principles — Business at Santa Ana College.",
      "url": "https://www.sac.edu/"
    },
    {
      "code": "BUS 157",
      "title": "Accounting Principles",
      "modality": "in_person",
      "term": "Fall 2026",
      "units": "5",
      "instructor": "Johnson",
      "section": "02",
      "description": "Accounting Principles — Business at Santa Ana College.",
      "url": "https://www.sac.edu/"
    },
    {
      "code": "BUS 157",
      "title": "Accounting Principles",
      "modality": "online",
      "term": "Fall 2026",
      "units": "5",
      "instructor": "Wong",
      "section": "03",
      "description": "Accounting Principles — Business at Santa Ana College.",
      "url": "https://www.sac.edu/"
    },
    {
      "code": "ART 187",
      "title": "Art History",
      "modality": "in_person",
      "term": "Fall 2026",
      "units": "1",
      "instructor": "Rivera",
      "section": "01H",
      "description": "Art History — Art at Santa Ana College.",
      "url": "https://www.sac.edu/"
    },
    {
      "code": "ART 187",
      "title": "Art History",
      "modality": "in_person",
      "term": "Fall 2026",
      "units": "1",
      "instructor": "Anderson",
      "section": "02H",
      "description": "Art History — Art at Santa Ana College.",
      "url": "https://www.sac.edu/"
    },
    {
      "code": "ART 119",
      "title": "Drawing I",
      "modality": "online",
      "term": "Fall 2026",
      "units": "2",
      "instructor": "Martinez",
      "section": "01H",
      "description": "Drawing I — Art at Santa Ana College.",
      "url": "https://www.sac.edu/"
    },
    {
      "code": "ART 284",
      "title": "Digital Photography",
      "modality": "in_person",
      "term": "Fall 2026",
      "units": "1",
      "instructor": "Nguyen",
      "section": "01W",
      "description": "Digital Photography — Art at Santa Ana College.",
      "url": "https://www.sac.edu/"
    },
    {
      "code": "ART 284",
      "title": "Digital Photography",
      "modality": "hybrid",
      "term": "Fall 2026",
      "units": "1",
      "instructor": "Garcia",
      "section": "02W",
      "description": "Digital Photography — Art at Santa Ana College.",
      "url": "https://www.sac.edu/"
    },
    {
      "code": "ART 127",
      "title": "Ceramics",
      "modality": "online",
      "term": "Fall 2026",
      "units": "5",
      "instructor": "Anderson",
      "section": "01H",
      "description": "Ceramics — Art at Santa Ana College.",
      "url": "https://www.sac.edu/"
    },
    {
      "code": "ART 127",
      "title": "Ceramics",
      "modality": "hybrid",
      "term": "Fall 2026",
      "units": "1",
      "instructor": "Khan",
      "section": "02W",
      "description": "Ceramics — Art at Santa Ana College.",
      "url": "https://www.sac.edu/"
    },
    {
      "code": "HIST 168",
      "title": "US History",
      "modality": "hybrid",
      "term": "Fall 2026",
      "units": "1",
      "instructor": "Smith",
      "section": "01W",
      "description": "US History — History at Santa Ana College.",
      "url": "https://www.sac.edu/"
    },
    {
      "code": "HIST 212",
      "title": "World History",
      "modality": "online",
      "term": "Fall 2026",
      "units": "5",
      "instructor": "Martinez",
      "section": "01N",
      "description": "World History — History at Santa Ana College.",
      "url": "https://www.sac.edu/"
    },
    {
      "code": "HIST 212",
      "title": "World History",
      "modality": "hybrid",
      "term": "Fall 2026",
      "units": "3",
      "instructor": "Martinez",
      "section": "02W",
      "description": "World History — History at Santa Ana College.",
      "url": "https://www.sac.edu/"
    },
    {
      "code": "HIST 212",
      "title": "World History",
      "modality": "hybrid",
      "term": "Fall 2026",
      "units": "4",
      "instructor": "Brown",
      "section": "03W",
      "description": "World History — History at Santa Ana College.",
      "url": "https://www.sac.edu/"
    },
    {
      "code": "HIST 253",
      "title": "California History",
      "modality": "online",
      "term": "Fall 2026",
      "units": "3",
      "instructor": "Smith",
      "section": "01W",
      "description": "California History — History at Santa Ana College.",
      "url": "https://www.sac.edu/"
    },
    {
      "code": "HIST 253",
      "title": "California History",
      "modality": "hybrid",
      "term": "Fall 2026",
      "units": "4",
      "instructor": "Brown",
      "section": "02W",
      "description": "California History — History at Santa Ana College.",
      "url": "https://www.sac.edu/"
    },
    {
      "code": "HIST 253",
      "title": "California History",
      "modality": "online",
      "term": "Fall 2026",
      "units": "2",
      "instructor": "Chen",
      "section": "03W",
      "description": "California History — History at Santa Ana College.",
      "url": "https://www.sac.edu/"
    },
    {
      "code": "COMM 278",
      "title": "Interpersonal Communication",
      "modality": "hybrid",
      "term": "Fall 2026",
      "units": "3",
      "instructor": "Davis",
      "section": "01N",
      "description": "Interpersonal Communication — Communication Studies at Santa Ana College.",
      "url": "https://www.sac.edu/"
    },
    {
      "code": "COMM 142",
      "title": "Mass Media",
      "modality": "online",
      "term": "Fall 2026",
      "units": "1",
      "instructor": "Garcia",
      "section": "01N",
      "description": "Mass Media — Communication Studies at Santa Ana College.",
      "url": "https://www.sac.edu/"
    },
    {
      "code": "COMM 142",
      "title": "Mass Media",
      "modality": "hybrid",
      "term": "Fall 2026",
      "units": "3",
      "instructor": "Patel",
      "section": "02H",
      "description": "Mass Media — Communication Studies at Santa Ana College.",
      "url": "https://www.sac.edu/"
    },
    {
      "code": "COMM 142",
      "title": "Mass Media",
      "modality": "in_person",
      "term": "Fall 2026",
      "units": "1",
      "instructor": "Lopez",
      "section": "03",
      "description": "Mass Media — Communication Studies at Santa Ana College.",
      "url": "https://www.sac.edu/"
    },
    {
      "code": "COMM 204",
      "title": "Small Group Communication",
      "modality": "in_person",
      "term": "Fall 2026",
      "units": "3",
      "instructor": "Martinez",
      "section": "01W",
      "description": "Small Group Communication — Communication Studies at Santa Ana College.",
      "url": "https://www.sac.edu/"
    },
    {
      "code": "COMM 204",
      "title": "Small Group Communication",
      "modality": "online",
      "term": "Fall 2026",
      "units": "2",
      "instructor": "Martinez",
      "section": "02W",
      "description": "Small Group Communication — Communication Studies at Santa Ana College.",
      "url": "https://www.sac.edu/"
    },
    {
      "code": "COMM 204",
      "title": "Small Group Communication",
      "modality": "in_person",
      "term": "Fall 2026",
      "units": "3",
      "instructor": "Rivera",
      "section": "03N",
      "description": "Small Group Communication — Communication Studies at Santa Ana College.",
      "url": "https://www.sac.edu/"
    },
    {
      "code": "SPAN 254",
      "title": "Elementary Spanish",
      "modality": "hybrid",
      "term": "Fall 2026",
      "units": "2",
      "instructor": "Smith",
      "section": "01W",
      "description": "Elementary Spanish — Spanish at Santa Ana College.",
      "url": "https://www.sac.edu/"
    },
    {
      "code": "SPAN 254",
      "title": "Elementary Spanish",
      "modality": "online",
      "term": "Fall 2026",
      "units": "2",
      "instructor": "Nguyen",
      "section": "02N",
      "description": "Elementary Spanish — Spanish at Santa Ana College.",
      "url": "https://www.sac.edu/"
    },
    {
      "code": "SPAN 254",
      "title": "Elementary Spanish",
      "modality": "online",
      "term": "Fall 2026",
      "units": "3",
      "instructor": "Lee",
      "section": "03N",
      "description": "Elementary Spanish — Spanish at Santa Ana College.",
      "url": "https://www.sac.edu/"
    },
    {
      "code": "SPAN 209",
      "title": "Spanish for Heritage Speakers",
      "modality": "in_person",
      "term": "Fall 2026",
      "units": "4",
      "instructor": "Lopez",
      "section": "01",
      "description": "Spanish for Heritage Speakers — Spanish at Santa Ana College.",
      "url": "https://www.sac.edu/"
    },
    {
      "code": "SPAN 209",
      "title": "Spanish for Heritage Speakers",
      "modality": "in_person",
      "term": "Fall 2026",
      "units": "2",
      "instructor": "Nguyen",
      "section": "02W",
      "description": "Spanish for Heritage Speakers — Spanish at Santa Ana College.",
      "url": "https://www.sac.edu/"
    },
    {
      "code": "NURS 250",
      "title": "Fundamentals of Nursing",
      "modality": "in_person",
      "term": "Fall 2026",
      "units": "1",
      "instructor": "Khan",
      "section": "01H",
      "description": "Fundamentals of Nursing — Nursing at Santa Ana College.",
      "url": "https://www.sac.edu/"
    },
    {
      "code": "NURS 250",
      "title": "Fundamentals of Nursing",
      "modality": "in_person",
      "term": "Fall 2026",
      "units": "3",
      "instructor": "Brown",
      "section": "02N",
      "description": "Fundamentals of Nursing — Nursing at Santa Ana College.",
      "url": "https://www.sac.edu/"
    },
    {
      "code": "NURS 250",
      "title": "Fundamentals of Nursing",
      "modality": "online",
      "term": "Fall 2026",
      "units": "4",
      "instructor": "Lopez",
      "section": "03H",
      "description": "Fundamentals of Nursing — Nursing at Santa Ana College.",
      "url": "https://www.sac.edu/"
    },
    {
      "code": "NURS 206",
      "title": "Medical-Surgical Nursing",
      "modality": "online",
      "term": "Fall 2026",
      "units": "4",
      "instructor": "Lopez",
      "section": "01N",
      "description": "Medical-Surgical Nursing — Nursing at Santa Ana College.",
      "url": "https://www.sac.edu/"
    },
    {
      "code": "NURS 206",
      "title": "Medical-Surgical Nursing",
      "modality": "hybrid",
      "term": "Fall 2026",
      "units": "1",
      "instructor": "Nguyen",
      "section": "02W",
      "description": "Medical-Surgical Nursing — Nursing at Santa Ana College.",
      "url": "https://www.sac.edu/"
    },
    {
      "code": "NURS 263",
      "title": "Pharmacology",
      "modality": "online",
      "term": "Fall 2026",
      "units": "1",
      "instructor": "Rivera",
      "section": "01H",
      "description": "Pharmacology — Nursing at Santa Ana College.",
      "url": "https://www.sac.edu/"
    },
    {
      "code": "NURS 243",
      "title": "Maternal-Newborn Nursing",
      "modality": "online",
      "term": "Fall 2026",
      "units": "5",
      "instructor": "Brown",
      "section": "01",
      "description": "Maternal-Newborn Nursing — Nursing at Santa Ana College.",
      "url": "https://www.sac.edu/"
    },
    {
      "code": "KIN 110",
      "title": "Introduction to Kinesiology",
      "modality": "hybrid",
      "term": "Fall 2026",
      "units": "1",
      "instructor": "Patel",
      "section": "01H",
      "description": "Introduction to Kinesiology — Kinesiology at Santa Ana College.",
      "url": "https://www.sac.edu/"
    },
    {
      "code": "KIN 110",
      "title": "Introduction to Kinesiology",
      "modality": "online",
      "term": "Fall 2026",
      "units": "5",
      "instructor": "Anderson",
      "section": "02H",
      "description": "Introduction to Kinesiology — Kinesiology at Santa Ana College.",
      "url": "https://www.sac.edu/"
    },
    {
      "code": "KIN 254",
      "title": "Personal Fitness",
      "modality": "hybrid",
      "term": "Fall 2026",
      "units": "3",
      "instructor": "Brown",
      "section": "01N",
      "description": "Personal Fitness — Kinesiology at Santa Ana College.",
      "url": "https://www.sac.edu/"
    },
    {
      "code": "KIN 254",
      "title": "Personal Fitness",
      "modality": "in_person",
      "term": "Fall 2026",
      "units": "3",
      "instructor": "Wong",
      "section": "02",
      "description": "Personal Fitness — Kinesiology at Santa Ana College.",
      "url": "https://www.sac.edu/"
    },
    {
      "code": "KIN 182",
      "title": "First Aid and CPR",
      "modality": "in_person",
      "term": "Fall 2026",
      "units": "3",
      "instructor": "Anderson",
      "section": "01W",
      "description": "First Aid and CPR — Kinesiology at Santa Ana College.",
      "url": "https://www.sac.edu/"
    },
    {
      "code": "ECON 111",
      "title": "Macroeconomics",
      "modality": "in_person",
      "term": "Fall 2026",
      "units": "3",
      "instructor": "Anderson",
      "section": "01N",
      "description": "Macroeconomics — Economics at Santa Ana College.",
      "url": "https://www.sac.edu/"
    },
    {
      "code": "ECON 111",
      "title": "Macroeconomics",
      "modality": "hybrid",
      "term": "Fall 2026",
      "units": "1",
      "instructor": "Davis",
      "section": "02",
      "description": "Macroeconomics — Economics at Santa Ana College.",
      "url": "https://www.sac.edu/"
    },
    {
      "code": "ECON 268",
      "title": "Microeconomics",
      "modality": "in_person",
      "term": "Fall 2026",
      "units": "2",
      "instructor": "Chen",
      "section": "01H",
      "description": "Microeconomics — Economics at Santa Ana College.",
      "url": "https://www.sac.edu/"
    },
    {
      "code": "ECON 268",
      "title": "Microeconomics",
      "modality": "online",
      "term": "Fall 2026",
      "units": "1",
      "instructor": "Wong",
      "section": "02H",
      "description": "Microeconomics — Economics at Santa Ana College.",
      "url": "https://www.sac.edu/"
    },
    {
      "code": "ECON 268",
      "title": "Microeconomics",
      "modality": "hybrid",
      "term": "Fall 2026",
      "units": "4",
      "instructor": "Garcia",
      "section": "03H",
      "description": "Microeconomics — Economics at Santa Ana College.",
      "url": "https://www.sac.edu/"
    },
    {
      "code": "PHYS 172",
      "title": "Physics for Scientists and Engineers",
      "modality": "online",
      "term": "Fall 2026",
      "units": "4",
      "instructor": "Chen",
      "section": "01W",
      "description": "Physics for Scientists and Engineers — Physics at Santa Ana College.",
      "url": "https://www.sac.edu/"
    },
    {
      "code": "PHYS 172",
      "title": "Physics for Scientists and Engineers",
      "modality": "in_person",
      "term": "Fall 2026",
      "units": "4",
      "instructor": "Nguyen",
      "section": "02",
      "description": "Physics for Scientists and Engineers — Physics at Santa Ana College.",
      "url": "https://www.sac.edu/"
    },
    {
      "code": "PHYS 172",
      "title": "Physics for Scientists and Engineers",
      "modality": "hybrid",
      "term": "Fall 2026",
      "units": "3",
      "instructor": "Rivera",
      "section": "03W",
      "description": "Physics for Scientists and Engineers — Physics at Santa Ana College.",
      "url": "https://www.sac.edu/"
    },
    {
      "code": "PHYS 177",
      "title": "Astronomy",
      "modality": "hybrid",
      "term": "Fall 2026",
      "units": "5",
      "instructor": "Chen",
      "section": "01",
      "description": "Astronomy — Physics at Santa Ana College.",
      "url": "https://www.sac.edu/"
    }
  ]
}