{
  "slug": "college-of-alameda",
  "scrapedAt": "2026-06-05T22:55:19.412Z",
  "count": 87,
  "courses": [
    {
      "code": "CIS 146",
      "title": "Programming in Python",
      "modality": "online",
      "term": "Fall 2026",
      "units": "1",
      "instructor": "Lopez",
      "section": "01N",
      "description": "Programming in Python — Computer Information Systems at College of Alameda.",
      "url": "https://alameda.edu/"
    },
    {
      "code": "CIS 146",
      "title": "Programming in Python",
      "modality": "hybrid",
      "term": "Fall 2026",
      "units": "2",
      "instructor": "Smith",
      "section": "02N",
      "description": "Programming in Python — Computer Information Systems at College of Alameda.",
      "url": "https://alameda.edu/"
    },
    {
      "code": "CIS 175",
      "title": "Data Structures",
      "modality": "in_person",
      "term": "Fall 2026",
      "units": "1",
      "instructor": "Smith",
      "section": "01N",
      "description": "Data Structures — Computer Information Systems at College of Alameda.",
      "url": "https://alameda.edu/"
    },
    {
      "code": "CIS 175",
      "title": "Data Structures",
      "modality": "in_person",
      "term": "Fall 2026",
      "units": "1",
      "instructor": "Garcia",
      "section": "02H",
      "description": "Data Structures — Computer Information Systems at College of Alameda.",
      "url": "https://alameda.edu/"
    },
    {
      "code": "CIS 175",
      "title": "Data Structures",
      "modality": "in_person",
      "term": "Fall 2026",
      "units": "3",
      "instructor": "Garcia",
      "section": "03",
      "description": "Data Structures — Computer Information Systems at College of Alameda.",
      "url": "https://alameda.edu/"
    },
    {
      "code": "CIS 212",
      "title": "Web Development",
      "modality": "hybrid",
      "term": "Fall 2026",
      "units": "3",
      "instructor": "Nguyen",
      "section": "01N",
      "description": "Web Development — Computer Information Systems at College of Alameda.",
      "url": "https://alameda.edu/"
    },
    {
      "code": "CIS 212",
      "title": "Web Development",
      "modality": "hybrid",
      "term": "Fall 2026",
      "units": "2",
      "instructor": "Brown",
      "section": "02H",
      "description": "Web Development — Computer Information Systems at College of Alameda.",
      "url": "https://alameda.edu/"
    },
    {
      "code": "CIS 212",
      "title": "Web Development",
      "modality": "hybrid",
      "term": "Fall 2026",
      "units": "1",
      "instructor": "Johnson",
      "section": "03N",
      "description": "Web Development — Computer Information Systems at College of Alameda.",
      "url": "https://alameda.edu/"
    },
    {
      "code": "CIS 152",
      "title": "Cybersecurity Fundamentals",
      "modality": "in_person",
      "term": "Fall 2026",
      "units": "5",
      "instructor": "Nguyen",
      "section": "01",
      "description": "Cybersecurity Fundamentals — Computer Information Systems at College of Alameda.",
      "url": "https://alameda.edu/"
    },
    {
      "code": "CIS 152",
      "title": "Cybersecurity Fundamentals",
      "modality": "online",
      "term": "Fall 2026",
      "units": "4",
      "instructor": "Patel",
      "section": "02W",
      "description": "Cybersecurity Fundamentals — Computer Information Systems at College of Alameda.",
      "url": "https://alameda.edu/"
    },
    {
      "code": "CIS 295",
      "title": "JavaScript Programming",
      "modality": "in_person",
      "term": "Fall 2026",
      "units": "2",
      "instructor": "Wong",
      "section": "01N",
      "description": "JavaScript Programming — Computer Information Systems at College of Alameda.",
      "url": "https://alameda.edu/"
    },
    {
      "code": "CIS 295",
      "title": "JavaScript Programming",
      "modality": "in_person",
      "term": "Fall 2026",
      "units": "5",
      "instructor": "Anderson",
      "section": "02H",
      "description": "JavaScript Programming — Computer Information Systems at College of Alameda.",
      "url": "https://alameda.edu/"
    },
    {
      "code": "MATH 180",
      "title": "College Algebra",
      "modality": "hybrid",
      "term": "Fall 2026",
      "units": "4",
      "instructor": "Rivera",
      "section": "01W",
      "description": "College Algebra — Mathematics at College of Alameda.",
      "url": "https://alameda.edu/"
    },
    {
      "code": "MATH 180",
      "title": "College Algebra",
      "modality": "in_person",
      "term": "Fall 2026",
      "units": "3",
      "instructor": "Davis",
      "section": "02W",
      "description": "College Algebra — Mathematics at College of Alameda.",
      "url": "https://alameda.edu/"
    },
    {
      "code": "MATH 216",
      "title": "Precalculus",
      "modality": "hybrid",
      "term": "Fall 2026",
      "units": "4",
      "instructor": "Lee",
      "section": "01H",
      "description": "Precalculus — Mathematics at College of Alameda.",
      "url": "https://alameda.edu/"
    },
    {
      "code": "MATH 216",
      "title": "Precalculus",
      "modality": "online",
      "term": "Fall 2026",
      "units": "1",
      "instructor": "Brown",
      "section": "02N",
      "description": "Precalculus — Mathematics at College of Alameda.",
      "url": "https://alameda.edu/"
    },
    {
      "code": "MATH 246",
      "title": "Trigonometry",
      "modality": "in_person",
      "term": "Fall 2026",
      "units": "1",
      "instructor": "Lopez",
      "section": "01N",
      "description": "Trigonometry — Mathematics at College of Alameda.",
      "url": "https://alameda.edu/"
    },
    {
      "code": "MATH 246",
      "title": "Trigonometry",
      "modality": "in_person",
      "term": "Fall 2026",
      "units": "2",
      "instructor": "Wong",
      "section": "02",
      "description": "Trigonometry — Mathematics at College of Alameda.",
      "url": "https://alameda.edu/"
    },
    {
      "code": "MATH 267",
      "title": "Linear Algebra",
      "modality": "hybrid",
      "term": "Fall 2026",
      "units": "2",
      "instructor": "Khan",
      "section": "01H",
      "description": "Linear Algebra — Mathematics at College of Alameda.",
      "url": "https://alameda.edu/"
    },
    {
      "code": "MATH 264",
      "title": "Discrete Mathematics",
      "modality": "online",
      "term": "Fall 2026",
      "units": "1",
      "instructor": "Rivera",
      "section": "01",
      "description": "Discrete Mathematics — Mathematics at College of Alameda.",
      "url": "https://alameda.edu/"
    },
    {
      "code": "MATH 264",
      "title": "Discrete Mathematics",
      "modality": "in_person",
      "term": "Fall 2026",
      "units": "5",
      "instructor": "Johnson",
      "section": "02N",
      "description": "Discrete Mathematics — Mathematics at College of Alameda.",
      "url": "https://alameda.edu/"
    },
    {
      "code": "ENGL 118",
      "title": "College Composition",
      "modality": "hybrid",
      "term": "Fall 2026",
      "units": "3",
      "instructor": "Davis",
      "section": "01H",
      "description": "College Composition — English at College of Alameda.",
      "url": "https://alameda.edu/"
    },
    {
      "code": "ENGL 118",
      "title": "College Composition",
      "modality": "in_person",
      "term": "Fall 2026",
      "units": "3",
      "instructor": "Lee",
      "section": "02",
      "description": "College Composition — English at College of Alameda.",
      "url": "https://alameda.edu/"
    },
    {
      "code": "ENGL 118",
      "title": "College Composition",
      "modality": "in_person",
      "term": "Fall 2026",
      "units": "3",
      "instructor": "Khan",
      "section": "03W",
      "description": "College Composition — English at College of Alameda.",
      "url": "https://alameda.edu/"
    },
    {
      "code": "ENGL 227",
      "title": "Critical Thinking",
      "modality": "hybrid",
      "term": "Fall 2026",
      "units": "4",
      "instructor": "Lopez",
      "section": "01",
      "description": "Critical Thinking — English at College of Alameda.",
      "url": "https://alameda.edu/"
    },
    {
      "code": "ENGL 227",
      "title": "Critical Thinking",
      "modality": "hybrid",
      "term": "Fall 2026",
      "units": "5",
      "instructor": "Anderson",
      "section": "02H",
      "description": "Critical Thinking — English at College of Alameda.",
      "url": "https://alameda.edu/"
    },
    {
      "code": "ENGL 227",
      "title": "Critical Thinking",
      "modality": "hybrid",
      "term": "Fall 2026",
      "units": "2",
      "instructor": "Martinez",
      "section": "03W",
      "description": "Critical Thinking — English at College of Alameda.",
      "url": "https://alameda.edu/"
    },
    {
      "code": "ENGL 221",
      "title": "American Literature",
      "modality": "in_person",
      "term": "Fall 2026",
      "units": "1",
      "instructor": "Garcia",
      "section": "01N",
      "description": "American Literature — English at College of Alameda.",
      "url": "https://alameda.edu/"
    },
    {
      "code": "ENGL 117",
      "title": "Technical Writing",
      "modality": "online",
      "term": "Fall 2026",
      "units": "3",
      "instructor": "Johnson",
      "section": "01N",
      "description": "Technical Writing — English at College of Alameda.",
      "url": "https://alameda.edu/"
    },
    {
      "code": "ENGL 170",
      "title": "Introduction to Poetry",
      "modality": "in_person",
      "term": "Fall 2026",
      "units": "1",
      "instructor": "Martinez",
      "section": "01H",
      "description": "Introduction to Poetry — English at College of Alameda.",
      "url": "https://alameda.edu/"
    },
    {
      "code": "ENGL 170",
      "title": "Introduction to Poetry",
      "modality": "in_person",
      "term": "Fall 2026",
      "units": "3",
      "instructor": "Chen",
      "section": "02H",
      "description": "Introduction to Poetry — English at College of Alameda.",
      "url": "https://alameda.edu/"
    },
    {
      "code": "BIOL 193",
      "title": "General Biology",
      "modality": "online",
      "term": "Fall 2026",
      "units": "1",
      "instructor": "Smith",
      "section": "01W",
      "description": "General Biology — Biology at College of Alameda.",
      "url": "https://alameda.edu/"
    },
    {
      "code": "BIOL 193",
      "title": "General Biology",
      "modality": "online",
      "term": "Fall 2026",
      "units": "4",
      "instructor": "Johnson",
      "section": "02H",
      "description": "General Biology — Biology at College of Alameda.",
      "url": "https://alameda.edu/"
    },
    {
      "code": "BIOL 166",
      "title": "Human Anatomy",
      "modality": "online",
      "term": "Fall 2026",
      "units": "5",
      "instructor": "Smith",
      "section": "01",
      "description": "Human Anatomy — Biology at College of Alameda.",
      "url": "https://alameda.edu/"
    },
    {
      "code": "BIOL 166",
      "title": "Human Anatomy",
      "modality": "in_person",
      "term": "Fall 2026",
      "units": "1",
      "instructor": "Lee",
      "section": "02W",
      "description": "Human Anatomy — Biology at College of Alameda.",
      "url": "https://alameda.edu/"
    },
    {
      "code": "BIOL 166",
      "title": "Human Anatomy",
      "modality": "hybrid",
      "term": "Fall 2026",
      "units": "3",
      "instructor": "Wong",
      "section": "03",
      "description": "Human Anatomy — Biology at College of Alameda.",
      "url": "https://alameda.edu/"
    },
    {
      "code": "BIOL 168",
      "title": "Physiology",
      "modality": "hybrid",
      "term": "Fall 2026",
      "units": "4",
      "instructor": "Wong",
      "section": "01H",
      "description": "Physiology — Biology at College of Alameda.",
      "url": "https://alameda.edu/"
    },
    {
      "code": "BIOL 168",
      "title": "Physiology",
      "modality": "in_person",
      "term": "Fall 2026",
      "units": "4",
      "instructor": "Wong",
      "section": "02H",
      "description": "Physiology — Biology at College of Alameda.",
      "url": "https://alameda.edu/"
    },
    {
      "code": "BIOL 168",
      "title": "Physiology",
      "modality": "in_person",
      "term": "Fall 2026",
      "units": "1",
      "instructor": "Wong",
      "section": "03N",
      "description": "Physiology — Biology at College of Alameda.",
      "url": "https://alameda.edu/"
    },
    {
      "code": "BIOL 261",
      "title": "Genetics",
      "modality": "online",
      "term": "Fall 2026",
      "units": "1",
      "instructor": "Nguyen",
      "section": "01N",
      "description": "Genetics — Biology at College of Alameda.",
      "url": "https://alameda.edu/"
    },
    {
      "code": "BIOL 261",
      "title": "Genetics",
      "modality": "online",
      "term": "Fall 2026",
      "units": "1",
      "instructor": "Khan",
      "section": "02N",
      "description": "Genetics — Biology at College of Alameda.",
      "url": "https://alameda.edu/"
    },
    {
      "code": "BIOL 261",
      "title": "Genetics",
      "modality": "in_person",
      "term": "Fall 2026",
      "units": "3",
      "instructor": "Garcia",
      "section": "03W",
      "description": "Genetics — Biology at College of Alameda.",
      "url": "https://alameda.edu/"
    },
    {
      "code": "CHEM 254",
      "title": "General Chemistry",
      "modality": "hybrid",
      "term": "Fall 2026",
      "units": "1",
      "instructor": "Anderson",
      "section": "01H",
      "description": "General Chemistry — Chemistry at College of Alameda.",
      "url": "https://alameda.edu/"
    },
    {
      "code": "CHEM 254",
      "title": "General Chemistry",
      "modality": "in_person",
      "term": "Fall 2026",
      "units": "4",
      "instructor": "Garcia",
      "section": "02H",
      "description": "General Chemistry — Chemistry at College of Alameda.",
      "url": "https://alameda.edu/"
    },
    {
      "code": "CHEM 165",
      "title": "Organic Chemistry",
      "modality": "online",
      "term": "Fall 2026",
      "units": "2",
      "instructor": "Garcia",
      "section": "01N",
      "description": "Organic Chemistry — Chemistry at College of Alameda.",
      "url": "https://alameda.edu/"
    },
    {
      "code": "CHEM 102",
      "title": "Introductory Chemistry",
      "modality": "hybrid",
      "term": "Fall 2026",
      "units": "5",
      "instructor": "Chen",
      "section": "01N",
      "description": "Introductory Chemistry — Chemistry at College of Alameda.",
      "url": "https://alameda.edu/"
    },
    {
      "code": "CHEM 102",
      "title": "Introductory Chemistry",
      "modality": "online",
      "term": "Fall 2026",
      "units": "4",
      "instructor": "Smith",
      "section": "02",
      "description": "Introductory Chemistry — Chemistry at College of Alameda.",
      "url": "https://alameda.edu/"
    },
    {
      "code": "CHEM 102",
      "title": "Introductory Chemistry",
      "modality": "hybrid",
      "term": "Fall 2026",
      "units": "2",
      "instructor": "Rivera",
      "section": "03W",
      "description": "Introductory Chemistry — Chemistry at College of Alameda.",
      "url": "https://alameda.edu/"
    },
    {
      "code": "PSYC 162",
      "title": "Introduction to Psychology",
      "modality": "hybrid",
      "term": "Fall 2026",
      "units": "3",
      "instructor": "Garcia",
      "section": "01N",
      "description": "Introduction to Psychology — Psychology at College of Alameda.",
      "url": "https://alameda.edu/"
    },
    {
      "code": "PSYC 162",
      "title": "Introduction to Psychology",
      "modality": "online",
      "term": "Fall 2026",
      "units": "3",
      "instructor": "Lee",
      "section": "02H",
      "description": "Introduction to Psychology — Psychology at College of Alameda.",
      "url": "https://alameda.edu/"
    },
    {
      "code": "PSYC 161",
      "title": "Abnormal Psychology",
      "modality": "online",
      "term": "Fall 2026",
      "units": "4",
      "instructor": "Khan",
      "section": "01H",
      "description": "Abnormal Psychology — Psychology at College of Alameda.",
      "url": "https://alameda.edu/"
    },
    {
      "code": "PSYC 161",
      "title": "Abnormal Psychology",
      "modality": "online",
      "term": "Fall 2026",
      "units": "5",
      "instructor": "Lopez",
      "section": "02H",
      "description": "Abnormal Psychology — Psychology at College of Alameda.",
      "url": "https://alameda.edu/"
    },
    {
      "code": "PSYC 161",
      "title": "Abnormal Psychology",
      "modality": "in_person",
      "term": "Fall 2026",
      "units": "2",
      "instructor": "Brown",
      "section": "03H",
      "description": "Abnormal Psychology — Psychology at College of Alameda.",
      "url": "https://alameda.edu/"
    },
    {
      "code": "PSYC 180",
      "title": "Social Psychology",
      "modality": "in_person",
      "term": "Fall 2026",
      "units": "1",
      "instructor": "Smith",
      "section": "01N",
      "description": "Social Psychology — Psychology at College of Alameda.",
      "url": "https://alameda.edu/"
    },
    {
      "code": "ART 175",
      "title": "Art History",
      "modality": "online",
      "term": "Fall 2026",
      "units": "1",
      "instructor": "Lee",
      "section": "01",
      "description": "Art History — Art at College of Alameda.",
      "url": "https://alameda.edu/"
    },
    {
      "code": "ART 147",
      "title": "Drawing I",
      "modality": "in_person",
      "term": "Fall 2026",
      "units": "1",
      "instructor": "Lee",
      "section": "01N",
      "description": "Drawing I — Art at College of Alameda.",
      "url": "https://alameda.edu/"
    },
    {
      "code": "ART 147",
      "title": "Drawing I",
      "modality": "online",
      "term": "Fall 2026",
      "units": "5",
      "instructor": "Khan",
      "section": "02H",
      "description": "Drawing I — Art at College of Alameda.",
      "url": "https://alameda.edu/"
    },
    {
      "code": "ART 235",
      "title": "Ceramics",
      "modality": "in_person",
      "term": "Fall 2026",
      "units": "3",
      "instructor": "Anderson",
      "section": "01H",
      "description": "Ceramics — Art at College of Alameda.",
      "url": "https://alameda.edu/"
    },
    {
      "code": "ART 190",
      "title": "Graphic Design",
      "modality": "in_person",
      "term": "Fall 2026",
      "units": "4",
      "instructor": "Wong",
      "section": "01H",
      "description": "Graphic Design — Art at College of Alameda.",
      "url": "https://alameda.edu/"
    },
    {
      "code": "ART 190",
      "title": "Graphic Design",
      "modality": "online",
      "term": "Fall 2026",
      "units": "5",
      "instructor": "Smith",
      "section": "02",
      "description": "Graphic Design — Art at College of Alameda.",
      "url": "https://alameda.edu/"
    },
    {
      "code": "ART 190",
      "title": "Graphic Design",
      "modality": "online",
      "term": "Fall 2026",
      "units": "3",
      "instructor": "Patel",
      "section": "03",
      "description": "Graphic Design — Art at College of Alameda.",
      "url": "https://alameda.edu/"
    },
    {
      "code": "COMM 200",
      "title": "Mass Media",
      "modality": "online",
      "term": "Fall 2026",
      "units": "2",
      "instructor": "Davis",
      "section": "01W",
      "description": "Mass Media — Communication Studies at College of Alameda.",
      "url": "https://alameda.edu/"
    },
    {
      "code": "COMM 200",
      "title": "Mass Media",
      "modality": "online",
      "term": "Fall 2026",
      "units": "5",
      "instructor": "Smith",
      "section": "02N",
      "description": "Mass Media — Communication Studies at College of Alameda.",
      "url": "https://alameda.edu/"
    },
    {
      "code": "COMM 200",
      "title": "Mass Media",
      "modality": "hybrid",
      "term": "Fall 2026",
      "units": "1",
      "instructor": "Rivera",
      "section": "03N",
      "description": "Mass Media — Communication Studies at College of Alameda.",
      "url": "https://alameda.edu/"
    },
    {
      "code": "COMM 188",
      "title": "Small Group Communication",
      "modality": "online",
      "term": "Fall 2026",
      "units": "3",
      "instructor": "Wong",
      "section": "01H",
      "description": "Small Group Communication — Communication Studies at College of Alameda.",
      "url": "https://alameda.edu/"
    },
    {
      "code": "COMM 188",
      "title": "Small Group Communication",
      "modality": "in_person",
      "term": "Fall 2026",
      "units": "2",
      "instructor": "Anderson",
      "section": "02H",
      "description": "Small Group Communication — Communication Studies at College of Alameda.",
      "url": "https://alameda.edu/"
    },
    {
      "code": "COMM 188",
      "title": "Small Group Communication",
      "modality": "online",
      "term": "Fall 2026",
      "units": "3",
      "instructor": "Patel",
      "section": "03W",
      "description": "Small Group Communication — Communication Studies at College of Alameda.",
      "url": "https://alameda.edu/"
    },
    {
      "code": "NURS 205",
      "title": "Fundamentals of Nursing",
      "modality": "in_person",
      "term": "Fall 2026",
      "units": "2",
      "instructor": "Lopez",
      "section": "01N",
      "description": "Fundamentals of Nursing — Nursing at College of Alameda.",
      "url": "https://alameda.edu/"
    },
    {
      "code": "NURS 205",
      "title": "Fundamentals of Nursing",
      "modality": "hybrid",
      "term": "Fall 2026",
      "units": "4",
      "instructor": "Brown",
      "section": "02",
      "description": "Fundamentals of Nursing — Nursing at College of Alameda.",
      "url": "https://alameda.edu/"
    },
    {
      "code": "NURS 246",
      "title": "Pharmacology",
      "modality": "hybrid",
      "term": "Fall 2026",
      "units": "1",
      "instructor": "Davis",
      "section": "01W",
      "description": "Pharmacology — Nursing at College of Alameda.",
      "url": "https://alameda.edu/"
    },
    {
      "code": "NURS 246",
      "title": "Pharmacology",
      "modality": "online",
      "term": "Fall 2026",
      "units": "4",
      "instructor": "Martinez",
      "section": "02",
      "description": "Pharmacology — Nursing at College of Alameda.",
      "url": "https://alameda.edu/"
    },
    {
      "code": "NURS 246",
      "title": "Pharmacology",
      "modality": "online",
      "term": "Fall 2026",
      "units": "4",
      "instructor": "Davis",
      "section": "03",
      "description": "Pharmacology — Nursing at College of Alameda.",
      "url": "https://alameda.edu/"
    },
    {
      "code": "NURS 144",
      "title": "Maternal-Newborn Nursing",
      "modality": "online",
      "term": "Fall 2026",
      "units": "3",
      "instructor": "Wong",
      "section": "01",
      "description": "Maternal-Newborn Nursing — Nursing at College of Alameda.",
      "url": "https://alameda.edu/"
    },
    {
      "code": "NURS 144",
      "title": "Maternal-Newborn Nursing",
      "modality": "online",
      "term": "Fall 2026",
      "units": "3",
      "instructor": "Nguyen",
      "section": "02N",
      "description": "Maternal-Newborn Nursing — Nursing at College of Alameda.",
      "url": "https://alameda.edu/"
    },
    {
      "code": "NURS 144",
      "title": "Maternal-Newborn Nursing",
      "modality": "in_person",
      "term": "Fall 2026",
      "units": "5",
      "instructor": "Davis",
      "section": "03W",
      "description": "Maternal-Newborn Nursing — Nursing at College of Alameda.",
      "url": "https://alameda.edu/"
    },
    {
      "code": "KIN 232",
      "title": "Introduction to Kinesiology",
      "modality": "in_person",
      "term": "Fall 2026",
      "units": "4",
      "instructor": "Nguyen",
      "section": "01W",
      "description": "Introduction to Kinesiology — Kinesiology at College of Alameda.",
      "url": "https://alameda.edu/"
    },
    {
      "code": "KIN 226",
      "title": "Personal Fitness",
      "modality": "online",
      "term": "Fall 2026",
      "units": "4",
      "instructor": "Patel",
      "section": "01",
      "description": "Personal Fitness — Kinesiology at College of Alameda.",
      "url": "https://alameda.edu/"
    },
    {
      "code": "KIN 226",
      "title": "Personal Fitness",
      "modality": "hybrid",
      "term": "Fall 2026",
      "units": "5",
      "instructor": "Patel",
      "section": "02H",
      "description": "Personal Fitness — Kinesiology at College of Alameda.",
      "url": "https://alameda.edu/"
    },
    {
      "code": "KIN 133",
      "title": "Yoga",
      "modality": "online",
      "term": "Fall 2026",
      "units": "5",
      "instructor": "Chen",
      "section": "01W",
      "description": "Yoga — Kinesiology at College of Alameda.",
      "url": "https://alameda.edu/"
    },
    {
      "code": "KIN 133",
      "title": "Yoga",
      "modality": "in_person",
      "term": "Fall 2026",
      "units": "2",
      "instructor": "Lee",
      "section": "02N",
      "description": "Yoga — Kinesiology at College of Alameda.",
      "url": "https://alameda.edu/"
    },
    {
      "code": "ECON 221",
      "title": "Macroeconomics",
      "modality": "online",
      "term": "Fall 2026",
      "units": "3",
      "instructor": "Khan",
      "section": "01N",
      "description": "Macroeconomics — Economics at College of Alameda.",
      "url": "https://alameda.edu/"
    },
    {
      "code": "PHYS 142",
      "title": "General Physics",
      "modality": "hybrid",
      "term": "Fall 2026",
      "units": "1",
      "instructor": "Nguyen",
      "section": "01",
      "description": "General Physics — Physics at College of Alameda.",
      "url": "https://alameda.edu/"
    },
    {
      "code": "PHYS 142",
      "title": "General Physics",
      "modality": "online",
      "term": "Fall 2026",
      "units": "2",
      "instructor": "Garcia",
      "section": "02H",
      "description": "General Physics — Physics at College of Alameda.",
      "url": "https://alameda.edu/"
    },
    {
      "code": "PHYS 180",
      "title": "Physics for Scientists and Engineers",
      "modality": "in_person",
      "term": "Fall 2026",
      "units": "4",
      "instructor": "Khan",
      "section": "01N",
      "description": "Physics for Scientists and Engineers — Physics at College of Alameda.",
      "url": "https://alameda.edu/"
    },
    {
      "code": "PHYS 180",
      "title": "Physics for Scientists and Engineers",
      "modality": "hybrid",
      "term": "Fall 2026",
      "units": "1",
      "instructor": "Patel",
      "section": "02W",
      "description": "Physics for Scientists and Engineers — Physics at College of Alameda.",
      "url": "https://alameda.edu/"
    },
    {
      "code": "PHYS 180",
      "title": "Physics for Scientists and Engineers",
      "modality": "in_person",
      "term": "Fall 2026",
      "units": "5",
      "instructor": "Martinez",
      "section": "03N",
      "description": "Physics for Scientists and Engineers — Physics at College of Alameda.",
      "url": "https://alameda.edu/"
    },
    {
      "code": "PHYS 190",
      "title": "Astronomy",
      "modality": "online",
      "term": "Fall 2026",
      "units": "4",
      "instructor": "Lee",
      "section": "01N",
      "description": "Astronomy — Physics at College of Alameda.",
      "url": "https://alameda.edu/"
    }
  ]
}