{
  "slug": "moorpark-college",
  "name": "Moorpark College",
  "url": "https://www.moorparkcollege.edu/",
  "source": "web-search-deep",
  "platform": "unknown",
  "scheduleUrl": null,
  "catalogUrl": null,
  "extractUrl": null,
  "method": null,
  "sampleCount": 0,
  "modalityCoverage": 0,
  "candidates": [],
  "searchQuery": "Moorpark College schedule of classes",
  "searchResults": [],
  "blocked": null,
  "confidence": 0,
  "notes": "Searched the web (0 results) but no page yielded course data — the schedule is likely a bespoke search app. Top results saved above.",
  "learnedAt": "2026-06-09T04:30:55.765Z"
}